backwork_upload_softlayer-0.2.1.dist-info/METADATA
backwork_upload_softlayer-0.2.1.dist-info/RECORD
backwork_upload_softlayer-0.2.1.dist-info/WHEEL
backwork_upload_softlayer-0.2.1.dist-info/entry_points.txt
backwork_upload_softlayer-0.2.1.dist-info/top_level.txt
softlayer/__init__.py
softlayer/softlayer.py
