Metadata-Version: 2.1
Name: backwork-upload-softlayer
Version: 0.2.1
Summary: Backwork plug-in for Softlayer uploads.
Home-page: https://github.com/IBM/backwork-upload-softlayer
Author: Luiz Aoqui
Author-email: laoqui@ca.ibm.com
License: Apache 2
Platform: UNKNOWN
Classifier: Development Status :: 3 - Alpha
Classifier: Environment :: Console
Classifier: Intended Audience :: Developers
Classifier: Intended Audience :: System Administrators
Classifier: Operating System :: POSIX :: Linux
Classifier: Programming Language :: Python :: 2.7
Classifier: Programming Language :: Python :: 2 :: Only
Classifier: License :: OSI Approved :: Apache Software License
Classifier: Topic :: Database
Classifier: Topic :: System :: Archiving :: Backup
Classifier: Topic :: Utilities
Requires-Dist: backwork
Requires-Dist: softlayer-object-storage (==0.5.4)
